<?xml version="1.0" encoding="utf-8"?>
<text>

Пришла весна и 
	<cg>две маленькие травки</cg>
	, еще находясь 
	<p1>под землей</p1>
	, почувствовали, что 
	<t>не сегодня—завтра</t>
	 и они покажут 
	<p2>на Божий свет</p2>
	 свои зелененькие головки.
— Как это хорошо — выйти 
	<p1>из земли</p1>
	! — сказала 
	<c1>
		одна из 
		<cg>них</cg>
	</c1>
	. — Как рада буду 
	<c1>я</c1>
	 увидеть 
	<c2>солнце</c2>
	, 
	<cg>цветы</cg>
	, 
	<cg>деревья</cg>
	 и те чудесные 
	<cg>крылатые создания</cg>
	, которые перелетают 
	<px>с цветка на цветок</px>
	. Может быть, 
	<cg>некоторые из них</cg>
	 пролетят совсем 
	<p3>близко от меня</p3>
	 и тогда 
	<c1>я</c1>
	 увижу, как горят 
	<cg>их крылышки</cg>
	 
	<px>
		в лучах 
		<c2>солнца</c2>
	</px>
	. — Вырасти бы поскорей и посмотреть на ожидающие нас чудеса! 
	<c1>Я</c1>
	 так много слышала 
	<cg>о них</cg>
	 от 
	<cg>наших</cg>
	 
	<cg>соседей — многолетних растений</cg>
	.
— Ну, а 
	<c3>я</c3>
	 так вовсе не жду никаких чудес, — недовольно пробормотала 
	<c3>вторая травка</c3>
	. — Не понимаю, право, почему это 
	<c1>тебе</c1>
	 так хочется выйти 
	<p4>на волю</p4>
	? 
	<c3>Мне</c3>
	 хорошо и 
	<p1>здесь, в земле</p1>
	. И что за интерес видеть 
	<c2>солнце</c2>
	? Говорят, от 
	<c2>его</c2>
	 лучей сохнут 
	<cg>растения</cg>
	, а кроме 
	<cg>бабочек</cg>
	 и 
	<cg>мотыльков</cg>
	, о которых 
	<c1>ты</c1>
	 так любишь расспрашивать 
	<cg>соседей</cg>
	, водятся, по их же словам, [11]еще всякие 
	<cg>гусеницы</cg>
	 и 
	<cg>жуки</cg>
	, которые безжалостно объедают 
	<cg>наши</cg>
	 стебли и листья. 
	<c3>Я</c3>
	 уже представляю 
	<c3>себе</c3>
	, как 
	<cx>
		один из 
		<cg>них</cg>
	</cx>
	 прямо ползет 
	<p3>на меня</p3>
	… Какой ужас! Нет, гораздо лучше остаться как можно дольше 
	<p1>здесь</p1>
	, 
	<p1>под землей</p1>
	.
Так говорили между 
	<cg>собой</cg>
	 
	<cg>две маленькие травки</cg>
	, и прошло ровно 
	<t>столько дней, сколько было нужно</t>
	 для того, чтобы дух 
	<c4>жизни</c4>
	, вложенный в 
	<cg>их</cg>
	 семена, окреп и проложил 
	<cg>им</cg>
	 путь 
	<p4>к самой поверхности земли</p4>
	. 
	<c1>Веселая травка</c1>
	 постаралась сделать это 
	<t>как можно скорей</t>
	, а 
	<c3>недовольная</c3>
	 — 
	<t>как можно медленнее</t>
	.
— Ах, как хорошо, как хорошо! — воскликнула 
	<c1>первая</c1>
	. — 
	<c1>Я</c1>
	 вижу свет! Да, 
	<c1>я</c1>
	 узнаю всё, что 
	<c1>мне</c1>
	 рассказывали. Это 
	<c2>солнце</c2>
	, — это 
	<c2>оно</c2>
	 так приветливо сияет 
	<p4>наверху</p4>
	 и смотрит 
	<px>на нас</px>
	! А сколько выходит кругом 
	<cg>других маленьких зеленых головок</cg>
	! Как всё это чудесно! Как весела и прекрасна будет 
	<cg>
		наша 
		<c4>жизнь</c4>
	</cg>
	! Торопись же, расти скорее, — говорила 
	<c1>она</c1>
	 своей недовольной 
	<c3>подруге</c3>
	.
Наконец выглянула и 
	<c3>та</c3>
	.
— Не понимаю, что хорошего увидела 
	<c1>ты</c1>
	 
	<p4>здесь</p4>
	? — с раздражением проговорила 
	<c3>она</c3>
	. — И 
	<c2>это</c2>
	 называется 
	<c2>солнцем</c2>
	? 
	<c2>Это</c2>
	 просто какой-то светлый 
	<c2>кружок</c2>
	: к тому же 
	<px>на него</px>
	 больно смотреть! 
	<c3>Мне</c3>
	 холодно… 
	<c3>Я</c3>
	 вся дрожу… Ах, зачем 
	<c3>я</c3>
	 не могу вернуться 
	<p1>назад</p1>
	. И ко всему этому — не знать даже того, что ожидает нас 
	<t>впереди</t>
	.
Весенний ветерок затих, и 
	<cg>травки</cg>
	 замолчали.
Незаметно приходили и уходили 
	<cg>ночи и дни</cg>
	. 
	<cg>Обе травки</cg>
	 продолжали 
	<p3>рядом</p3>
	 расти, стебельки 
	<cg>их</cg>
	 делались всё длинней и длинней, и 
	<px>на них</px>
	 то и дело показывались всё новые и новые зеленые листки. 
	<p3>Вокруг</p3>
	 них качались 
	<cg>полевые цветы</cg>
	, летали 
	<cg>бабочки</cg>
	 и 
	<cg>стрекозы</cg>
	, жужжали и ползали разноцветные 
	<cg>мошки</cg>
	 и 
	<cg>жучки</cg>
	.
— 
	<t>Вчера</t>
	 
	<p3>около меня</p3>
	 распустилась красная 
	<c5>гвоздика</c5>
	, — радостно сказала веселая 
	<c1>травка</c1>
	 
	<c1>своей</c1>
	 
	<c3>подруге</c3>
	. — Цветок 
	<c5>её</c5>
	 похож на маленькую звезду, и 
	<c5>она</c5>
	 благоухает так нежно и сладко, [12]что самые красивые 
	<cg>бабочки</cg>
	 прилетают отдыхать 
	<px>на ней</px>
	. 
	<c1>Я</c1>
	 могу вдоволь любоваться и 
	<cg>ими</cg>
	 и 
	<c5>ей</c5>
	! А 
	<t>сегодня</t>
	 
	<px>
		на самую верхушку 
		<c1>моего</c1>
		 собственного стебелька
	</px>
	 сел маленький 
	<c6>мотылек</c6>
	. 
	<c6>Он</c6>
	 был весь голубой и так мило шевелил 
	<c6>своими</c6>
	 усиками! 
	<c1>Я</c1>
	 думаю — 
	<c6>он</c6>
	 прилетит еще раз! Какой это был чудный 
	<c6>мотылек</c6>
	!
— 
	<c1>Ты</c1>
	 вечно радуешься, не зная чему, — сердито возразила ворчливая 
	<c2>травка</c2>
	. — И вечно у 
	<c1>тебя</c1>
	 одни глупости 
	<p5>на уме</p5>
	. А между тем 
	<c4>жизнь</c4>
	 полна неприятностей! Вон, 
	<p3>недалеко от меня</p3>
	, цветет полевая 
	<c7>ромашка</c7>
	 и 
	<c3>мне</c3>
	 просто противно видеть этот гордо выпрямленный негнущийся стебелек и эти белые торчащие по сторонам лепестки! Не понимаю, чего 
	<c7>она</c7>
	 так гордится? Велика важность — попасть 
	<px>в аптеку</px>
	! И этот противный лекарственный запах! У 
	<c3>меня</c3>
	 от него просто мутится 
	<p5>в голове</p5>
	! Поскорей бы пришли 
	<cg>люди и сорвали</cg>
	 
	<c7>ее</c7>
	! Боюсь только, что по неосторожности 
	<cg>они</cg>
	 растопчут и 
	<c3>меня</c3>
	! Когда 
	<t>вчера</t>
	 
	<p6>по лугу</p6>
	 мчалась 
	<c8>корова</c8>
	, а 
	<c8>за ней</c8>
	 белобрысый 
	<cx>мальчуган</cx>
	 с прутом, 
	<c3>я</c3>
	 
	<t>всё время</t>
	 дрожала за 
	<c3>
		свою 
		<c4>жизнь</c4>
	</c3>
	… Что за ужасное существование! Вечно бояться и вечно ждать, что вот-вот что-нибудь случится с 
	<c3>тобой</c3>
	!..
— 
	<c3>Ты</c3>
	 оттого 
	<t>всегда</t>
	 недовольна, что не умеешь ценить 
	<c4>жизнь</c4>
	, — сказала веселая 
	<c1>травка</c1>
	. — Посмотри, какой чудный 
	<cx>закат</cx>
	, как нежно пахнут милые 
	<cg>цветы</cg>
	, как красивы скользящие по небу 
	<cg>облака</cg>
	! Может быть, 
	<t>завтра</t>
	 будет гроза, может быть, 
	<cx>кто-нибудь</cx>
	 сорвет или растопчет 
	<c1>меня</c1>
	, но всё же на 
	<c1>моем</c1>
	 стебельке качался голубой 
	<c6>мотылек</c6>
	 и 
	<cx>бабочка</cx>
	 с пестрыми крылышками пролетела совсем 
	<p3>около меня</p3>
	!
Неумолимо подвигались вперед 
	<cg>ночи и дни</cg>
	. Луг, на котором росли обе 
	<cg>травки</cg>
	, покрылся густой зеленой травой. 
	<p6>На нём</p6>
	 то 
	<p6>тут</p6>
	, то 
	<p6>там</p6>
	, пестрели полевые 
	<cg>цветы</cg>
	. И 
	<t>в этом году</t>
	 
	<cg>колокольчики</cg>
	 переросли 
	<cg>всех</cg>
	 и можно было 
	<px>издалека</px>
	 различить 
	<cg>их</cg>
	 лиловые, колеблемые ветром, головки.

	<t>Однажды рано утром</t>
	 вместе с восходом 
	<c2>солнца</c2>
	 пришли 
	<cg>косцы</cg>
	. 
	<cg>Они</cg>
	 выстроились 
	<px>в ряд</px>
	 и под ровные взмахи их блестевших 
	<px>
		на 
		<c2>солнце</c2>
	</px>
	 кос все 
	<cg>травы</cg>
	 и 
	<cg>цветы</cg>
	 падали подкошенные 
	<p4>на землю</p4>
	. Дошла очередь и до обеих 
	<cg>подруг</cg>
	.[13]
— Какая ужасная смерть! Зачем только появилась 
	<c3>я</c3>
	 
	<p2>на Божий свет</p2>
	! — в последний раз долетел 
	<p3>
		до веселой 
		<c1>травки</c1>
	</p3>
	 знакомый голос её вечно-недовольной 
	<c3>соседки</c3>
	.
«Прощай, милое 
	<c2>солнце</c2>
	, прощай, добрая 
	<cx>земля</cx>
	, прощайте, все 
	<cg>мотыльки</cg>
	 и 
	<cg>травки</cg>
	! Видно, пора и 
	<c1>мне</c1>
	 
	<px>в душистое сено</px>
	», подумала 
	<p5>про себя</p5>
	 веселая 
	<c1>травка</c1>
	 и, подкошенная, легла 
	<p4>на землю</p4>
	 
	<p3>рядом</p3>
	 со 
	<c1>своею</c1>
	 
	<c3>соседкой</c3>
	.

</text>
