<?xml version="1.0" encoding="utf-8"?>
<text>

3 части


	<c1>Сыны</c1>
	 стояли 
	<p1>у стенки</p1>
	 сверкая ногами, обутыми в шпоры. 
	<c1>Они</c1>
	 обрадовались и

сказали:

 

Обнародуй 
	<c1>нам</c1>
	 
	<c2>отец</c2>
	

Что такое есть 
	<c3>Потец</c3>
	.

 


	<c2>Отец</c2>
	, сверкая очами, отвечал 
	<c1>им</c1>
	:

 


	<c1>Вы</c1>
	 не путайте 
	<c1>сыны</c1>
	

День конца и дочь весны.

Страшен, синь и сед 
	<c3>Потец</c3>
	.


	<c2>
		Я 
		<c1>ваш</c1>
		 ангел
	</c2>
	. 
	<c2>Я отец</c2>
	.


	<c2>Я</c2>
	 
	<c3>его</c3>
	 жестокость знаю,


	<c4>Смерть</c4>
	 
	<c2>моя</c2>
	 уже близка.

На 
	<c2>главе моей</c2>
	 зияют

Плеши, лысины — тоска.

И если жизнь протянется,

То скоро не останется

Ни сокола ни волоска.

Знать 
	<c4>смерть</c4>
	 близка.

Знать глядь тоска.

 


	<c1>Сыновья</c1>
	, позвенев в колокольчики, загремели 
	<c1>в свои</c1>
	 языки:

Да 
	<c1>мы</c1>
	 
	<c2>тебя</c2>
	 не о том спрашиваем,


	<c1>Мы</c1>
	 
	<c1>наши</c1>
	 мысли как чертог вынашиваем.


	<c2>Ты</c2>
	 скажи-ка 
	<c1>нам</c1>
	 
	<c2>отец</c2>
	

Что такое есть 
	<c3>Потец</c3>
	.

 

И воскликнул 
	<c2>отец</c2>
	: Пролог,

А в Прологе главное 
	<c5>Бог</c5>
	.

Усните 
	<c1>сыны</c1>
	,

Посмотрите сны.

 


	<c1>Сыновья</c1>
	 легли спать. Спрятав 
	<px>в карман</px>
	 грибы. Казалось, что стены, и те были

послушны. Ах, да мало ли что казалось. Но в общем немногое и нам как и им казалось. Но

чу! Что это? 
	<c2>Отец</c2>
	 опять непрямо отвечал на вопрос. И вновь проснувшимся 
	<c1>сыновьям</c1>
	 
	<c2>он</c2>
	

сказал вот что, восклицая и сверкая бровями:

 

Пускай поёт и пляшет


	<cg>Седой народ</cg>
	.

Пускай руками машет

Как человек.

 


	<tx>В мирный день блаженства</tx>
	

Ты истекаешь.

Как скоро 
	<c4>смерти</c4>
	 совершенство


	<c2>Я сам</c2>
	 постигну.

 

Несутся лошади как волны,

Стучат подковы.

Лихие кони жаром полны

Исчезнув скачут.

 

Но где ж понять исчезновенье,

И все ль мы смертны?

Что сообщишь ты мне мгновенье,

Тебя ль пойму 
	<c2>я</c2>
	?

 

Кровать стоит 
	<c2>передо мною</c2>
	,


	<c2>Я</c2>
	 тихо лягу.

И уподоблюсь под стеною

Цветам и флагу.

 


	<c1>Сыны, сыны</c1>
	. 
	<c2>Мой</c2>
	 час приходит.


	<c2>Я</c2>
	 умираю. 
	<c2>Я</c2>
	 умираю.

Не ездите 
	<px>на пароходе</px>
	,

Всему конец.

 


	<c1>Сыновья</c1>
	, построясь в ряды, сверкая ногами, начинают танцевать кадриль.


	<c6>Первый сын</c6>
	, или 
	<c6>он же первая пара</c6>
	:

 

Что такое есть 
	<c3>Потец</c3>
	

Расскажите 
	<c6>мне</c6>
	 
	<c2>отец</c2>
	.

 


	<c7>Второй сын</c7>
	, или 
	<c7>он же вторая пара</c7>
	:

 

Может быть 
	<c3>Потец свинец</c3>
	


	<c3>И младенец</c3>
	 
	<c3>и венец</c3>
	.

 


	<c8>Третий сын</c8>
	, или 
	<c8>он же третья пара</c8>
	:

 

Не могу понять 
	<c2>отец</c2>
	,

Где 
	<c3>он</c3>
	? кто же 
	<c3>он, Потец</c3>
	?

 


	<c2>Отец</c2>
	, сверкая очами, грозно стонет:

 

Ох 
	<px>в подушках</px>
	 
	<c2>я</c2>
	 лежу.

 


	<c6>Первый сын</c6>
	:

 

Эх 
	<c2>отец</c2>
	, держу жужу.


	<c2>Ты</c2>
	 не должен умереть,


	<c2>Ты</c2>
	 сначала клеть ответь.

 


	<c7>Второй сын</c7>
	, танцуя как верноподданный:

 


	<c3>Ах, Потец, Потец, Потец</c3>
	.


	<c2>Ах, отец, отец, отец</c2>
	.

 


	<c8>И третий сын</c8>
	, танцуя как выстрел:

 

Куклы все туша колпак,


	<c8>Я челнок челнок челнак</c8>
	.

 


	<c1>Сыновья</c1>
	 прекращают танцевать — не вечно же веселиться, и садятся молча и

тихо 
	<px>возле погасшей кровати отца</px>
	. 
	<c1>Они</c1>
	 глядят 
	<c2>в его увядающие очи</c2>
	. 
	<c1>Им</c1>
	 хочется всё

повторить. 
	<c2>Отец</c2>
	 умирает. 
	<c2>Он</c2>
	 становится крупным как гроздь винограда. 
	<c9>Нам</c9>
	 страшно

поглядеть 
	<c2>в его, что называется, лицо</c2>
	. 
	<c1>Сыновья</c1>
	 негласно и бесшумно входят 
	<c1>каждый</c1>
	 
	<p1>в

свою суеверную стену</p1>
	.

 


	<c3>Потец это холодный пот, выступающий на лбу умершего</c3>
	. 
	<c3>Это роса смерти, вот что такое Потец</c3>
	.

 

Часть вторая
 


	<c2>Отец</c2>
	 летает 
	<p2>над письменным столом</p2>
	. Но не думайте, 
	<c2>он не дух</c2>
	.

 


	<c2>Я</c2>
	 видел пожалуйте 
	<c10>розу</c10>
	,


	<c10>Сей скучный земли лепесток</c10>
	.

Последние мысли, казалось,

Додумывал 
	<c10>этот цветок</c10>
	.

 


	<c10>Он</c10>
	 горы соседние гладил

Последним дыханьем души.


	<c10>Над ним</c10>
	 проплывали княгини

И звёзды 
	<px>в небесной глуши</px>
	.

 


	<c1>Мои сыновья</c1>
	 удалились,

И лошадь 
	<c1>моя</c1>
	 как волна

Стояла и била копытом,

А рядом желтела луна.

 


	<c10>Цветок убеждённый блаженства</c10>
	,

Приблизился 
	<c5>Божеский</c5>
	 час.

Весь мир как заря наступает,

А 
	<c2>я</c2>
	 словно пламя погас.

 


	<c2>Отец</c2>
	 перестаёт говорить стихами и закуривает свечу, держа её в зубах как

флейту. При этом 
	<c2>он подушкой</c2>
	 опускается 
	<px>в кресло</px>
	.

Входит 
	<c6>первый сын</c6>
	 и говорит: Не ответил же 
	<c2>он</c2>
	 на вопросы. Поэтому 
	<c6>он</c6>
	 сразу

обращается 
	<c2>к подушке</c2>
	 с вопросом:

 


	<c2>Подушка подушка</c2>
	

Ответь наконец

Что такое есть 
	<c3>Потец</c3>
	.

 


	<c2>Подушка, она же отец</c2>
	:

 


	<c2>Я</c2>
	 знаю. 3наю!

 


	<c7>Второй сын</c7>
	 спрашивает второпях:

 

Так отвечай же,

Почто безмолвствуешь.

 


	<c8>Третий сын</c8>
	 совершенно распалён:

 

Напрасно вдовствуешь


	<c2>Уютная подушка</c2>
	.

Давай ответ.

 


	<c6>Первый сын</c6>
	:

 

Отвечай же.

 


	<c7>Второй сын</c7>
	:

 

Огня сюда, огня!

 


	<c8>Третий сын</c8>
	:

 


	<c8>Я</c8>
	 сейчас кого-нибудь повешу:

 


	<c2>Подушка, она же отец</c2>
	:

 

Немного терпенья,

Может быть 
	<c2>я</c2>
	 на всё и отвечу.

Хотел бы послушать пенье,

Тогда смогу разговаривать.

 


	<c2>Я</c2>
	 очень устал.

Искусство дало бы 
	<c2>мне</c2>
	 новые силы.

Прощай пьедестал,


	<c2>Я</c2>
	 хочу послушать 
	<c1>ваши голоса</c1>
	 
	<c11>под музыку</c11>
	.

 

Тогда 
	<c1>сыновья</c1>
	 не смогли отказать этой потрясённой просьбе 
	<c2>отца</c2>
	. 
	<c1>Они</c1>
	 стали

гуртом как скот и спели 
	<c11>всеобщую песню</c11>
	.

 


	<c11>Был брат брит Брут Римлянин чудесный. Все врут. Все мрут. Это был первый куплет. Второй куплет: Пел пил пробегал Один канатоходец. Он акробат. Он галл. Третий куплет: Иноходец С того света Дожидается рассвета</c11>
	.

И пока 
	<c1>они</c1>
	 пели, играла чудная, превосходная, всё и вся покоряющая 
	<c11>музыка</c11>
	. И

казалось, что разным чувствам есть ещё место на земле. Как чудо стояли 
	<c1>сыновья</c1>
	 вокруг

невзрачной 
	<c2>подушки</c2>
	 и ждали с бессмысленной надеждой ответа на свой незавидный и

дикий, внушительный вопрос: что такое 
	<c3>Потец</c3>
	? А 
	<c2>подушка</c2>
	 то порхала, то взвивалась

свечкою 
	<p4>в поднебесье</p4>
	, то как Днепр бежала 
	<p5>по комнате</p5>
	. 
	<c2>Отец</c2>
	 сидел 
	<p2>над письменным как Иван да Марья столом</p2>
	, а 
	<c1>сыновья</c1>
	 словно зонты стояли 
	<p1>у стенки</p1>
	. Вот что такое 
	<c3>Потец</c3>
	.

 

Часть третья
 


	<c2>Отец</c2>
	 сидел 
	<p3>на бронзовом коне</p3>
	, а 
	<c1>сыновья</c1>
	 стояли 
	<p3>по его бокам</p3>
	. А 
	<c8>третий сын</c8>
	 то

стоял 
	<p3>у хвоста</p3>
	, то 
	<p3>у лица лошади</p3>
	. Как видно и нам и ему, 
	<c8>он</c8>
	 не находил 
	<c8>себе</c8>
	 места. А

лошадь была как волна. 
	<c12>Никто</c12>
	 не произносил ни слова. 
	<c12>Все</c12>
	 разговаривали мыслями.

Тут 
	<c2>отец</c2>
	 сидя 
	<p3>на коне</p3>
	 и поглаживая милую утку, воскликнул мысленно и засверкал очами:

 

Всё ждёте что скажет 
	<c2>отец</c2>
	,

Объяснит ли 
	<c2>он</c2>
	 
	<c3>слово Потец</c3>
	.

Боже 
	<c2>я безутешный вдовец</c2>
	,


	<c2>Я безгрешный певец</c2>
	.

 


	<c6>Первый сын</c6>
	, нагибаясь, поднял 
	<px>с полу</px>
	 пятачок и простонал мысленно и засверкал ногами:

 


	<c2>Батюшка</c2>
	 наступает 
	<c4>конец</c4>
	.

Зрю на лбу 
	<c4>у тебя</c4>
	 венец.

Зря звонишь в бубенец.


	<c2>Ты уже леденец</c2>
	.

 


	<c7>Второй сын</c7>
	 был тоже очень омрачён, 
	<c7>он</c7>
	 нагнулся с другого бока и поднял дамский

ридикюль. 
	<c7>Он</c7>
	 заплакал мыслями и засверкал ногами:

 

Когда бы 
	<c7>я был жрец</c7>
	

Или 
	<c7>мертвец игрец</c7>
	,


	<c7>Я</c7>
	 
	<c5>Твой</c5>
	 посетил бы дворец


	<c5>О всесильный Творец</c5>
	.

 

А 
	<c8>третий сын</c8>
	 стоя 
	<p3>у хвоста лошади</p3>
	 и пощипывая 
	<c8>свои</c8>
	 усы мыслями, засверкал

ногами:

 

Где ключ от 
	<c8>моего</c8>
	 ума?

Где солнца луч,

Подаренный тобой зима?

 

А переместясь 
	<p3>к лицу лошади</p3>
	, которая была как волна, и поглаживая мыслями

волосы, засверкал ногами:

 

Бровей не видишь ты 
	<c2>отец</c2>
	,

Кровей каких пустых потец.

 

Тогда 
	<c2>отец</c2>
	 вынул 
	<px>из карманов</px>
	 дуло одного оружия и показывая его 
	<c1>детям</c1>
	,

воскликнул громко и радостно, сверкая очами:

 

Глядите: дуло,

И до чего ж его раздуло.

 


	<c6>Первый сын</c6>
	:

 

Где? покажи.

 


	<c7>Второй сын</c7>
	:

 

Везде. Как чижи.

 


	<c8>Третий сын</c8>
	:

 

Последний страх

Намедни

После обедни

Рассыпался в прах.

 

И 
	<tx>вдруг</tx>
	 открылись двери рая,

И 
	<c13>нянька</c13>
	 вышла 
	<px>из сарая</px>
	,

И был на ней надет чепец.

И это снова 
	<c12>всем</c12>
	 напомнило их вечный вопрос о том,

Что такое есть 
	<c3>Потец</c3>
	.

 


	<tx>Вмиг</tx>
	 наступила страшная тишина. Словно конфеты лежали 
	<c1>сыновья</c1>
	 поперёк ночной

комнаты, вращая белыми седыми затылками и сверкая ногами. Суеверие нашло 
	<c12>на всех</c12>
	.

 


	<c13>На</c13>
	 няньке был надет чепец,


	<c13>Она</c13>
	 висела как купец.

 

	<c13>Нянька</c13>
	 стала укладывать 
	<c2>отца</c2>
	 спать, 
	<c2>превратившегося в детскую косточку</c2>
	. 
	<c13>Она</c13>
	 пела 

	<c2>ему</c2>
	 
	<c11>песню</c11>
	:

 


	<c11>Над твоею колыбелью По губам плывёт слюна И живет луна. Над могилою над елью Спи тоскуй, Не просыпайся, Лучше рассыпайся. Эй кузнец куй! куй! Мы в кузнице уснём. Мы все узники</c11>
	.

 

И пока 
	<c13>она</c13>
	 пела, играла чудная, превосходная, всё и вся покоряющая 
	<c11>музыка</c11>
	. И

казалось, что разным чувствам есть ещё место на земле. Как чудо стоят 
	<c1>сыновья</c1>
	 возле

тихо погасшей кровати 
	<c2>отца</c2>
	. 
	<c1>Им</c1>
	 хочется всё повторить. 
	<c9>Нам</c9>
	 страшно поглядеть 
	<c2>в его, что называется, лицо</c2>
	. А 
	<c2>подушка</c2>
	 то порхала, то взвивалась свечкой 
	<p4>в поднебесье</p4>
	, то как

Днепр бежала 
	<p5>по комнате</p5>
	. 
	<c3>Потец это холодный пот, выступающий на лбу умершего</c3>
	. 
	<c3>Это роса смерти, вот что такое Потец</c3>
	.


	<c5>Господи</c5>
	, могли бы сказать 
	<c1>сыновья</c1>
	, если бы 
	<c1>они</c1>
	 могли. Ведь это 
	<c9>мы</c9>
	 уже знали

заранее.

</text>
